hebrew/__init__.py
hebrew/chars.py
hebrew/gematria.py
hebrew/grapheme_string.py
hebrew/hebrew_obj.py
hebrew/numerical_conversion/__init__.py
hebrew/numerical_conversion/convert.py
hebrew/numerical_conversion/mappings.py
hebrew/numerical_conversion/substitute.py
hebrew-0.8.1.dist-info/LICENSE
hebrew-0.8.1.dist-info/METADATA
hebrew-0.8.1.dist-info/WHEEL
hebrew-0.8.1.dist-info/RECORD
