Metadata-Version: 2.1
Name: hebrew
Version: 0.8.1
Summary: A python package with methods to handle the complexities of Hebrew text, calculate Gematria, and more.
Home-page: https://github.com/avi-perl/hebrew
License: MIT
Keywords: hebrew,gematria,grapheme,ivrit,yiddish,taamim,ta'amim,kabbalah
Author: Avi Perl
Author-email: avi@aviperl.me
Requires-Python: >=3.8.0,<4.0.0
Classifier: Development Status :: 4 - Beta
Classifier: Intended Audience :: Developers
Classifier: License :: OSI Approved :: MIT License
Classifier: Operating System :: MacOS
Classifier: Operating System :: Microsoft :: Windows
Classifier: Operating System :: POSIX :: Linux
Classifier: Programming Language :: Python :: 3
Classifier: Programming Language :: Python :: 3.8
Classifier: Programming Language :: Python :: 3.9
Classifier: Programming Language :: Python :: 3.10
Classifier: Programming Language :: Python :: 3.11
Classifier: Programming Language :: Python :: 3.12
Classifier: Typing :: Typed
Requires-Dist: grapheme (>=0.6.0,<0.7.0)
Project-URL: Documentation, https://hebrew.aviperl.me/
Project-URL: Repository, https://github.com/avi-perl/hebrew
